odoo8_addon_budget-8.0.1.1.0-py2.7-nspkg.pth
odoo8_addon_budget-8.0.1.1.0.dist-info/top_level.txt
odoo8_addon_budget-8.0.1.1.0.dist-info/WHEEL
odoo8_addon_budget-8.0.1.1.0.dist-info/RECORD
odoo8_addon_budget-8.0.1.1.0.dist-info/metadata.json
odoo8_addon_budget-8.0.1.1.0.dist-info/DESCRIPTION.rst
odoo8_addon_budget-8.0.1.1.0.dist-info/METADATA
odoo8_addon_budget-8.0.1.1.0.dist-info/namespace_packages.txt
odoo_addons/budget/budget_line.py
odoo_addons/budget/analytic_view.xml
odoo_addons/budget/__openerp__.py
odoo_addons/budget/budget_item.py
odoo_addons/budget/budget_view.xml
odoo_addons/budget/budget_version.py
odoo_addons/budget/budget.py
odoo_addons/budget/account.py
odoo_addons/budget/__init__.py
odoo_addons/budget/analytic.py
odoo_addons/budget/security/security.xml
odoo_addons/budget/security/ir.model.access.csv
odoo_addons/budget/i18n/zh_CN.po
odoo_addons/budget/i18n/ru.po
odoo_addons/budget/i18n/pt.po
odoo_addons/budget/i18n/it.po
odoo_addons/budget/i18n/es.po
odoo_addons/budget/i18n/tr.po
odoo_addons/budget/i18n/hr.po
odoo_addons/budget/i18n/bg.po
odoo_addons/budget/i18n/gl.po
odoo_addons/budget/i18n/budget.pot
odoo_addons/budget/i18n/ca.po
odoo_addons/budget/i18n/sl.po
odoo_addons/budget/i18n/es_ES.po
odoo_addons/budget/i18n/pt_PT.po
odoo_addons/budget/i18n/nl.po
odoo_addons/budget/i18n/am.po
odoo_addons/budget/i18n/de.po
odoo_addons/budget/i18n/fr.po
odoo_addons/budget/i18n/pt_BR.po
odoo_addons/budget/i18n/el_GR.po
odoo_addons/budget/i18n/fi.po
odoo_addons/budget/i18n/hr_HR.po
odoo_addons/budget/test/test_duplicate_budget.yml
odoo_addons/budget/test/test_analytic_amount.yml
odoo_addons/budget/test/test_default_end_date.yml
odoo_addons/budget/test/test_active_version.yml
odoo_addons/budget/demo/setup_user.yml
