Metadata-Version: 2.0
Name: odoo8-addon-budget
Version: 8.0.1.1.0
Summary: Multicurrency Analytic Budget
Home-page: http://camptocamp.com
Author: UNKNOWN
Author-email: UNKNOWN
License: UNKNOWN
Platform: UNKNOWN
Requires-Dist: odoo (<9.0a,>=8.0a)
Requires-Dist: odoo8-addon-analytic-multicurrency
Classifier: Programming Language :: Python :: 2.7
Classifier: Framework :: Odoo
